Receive/tester.v
//probador
`timescale 1ns/1ns

module probador(
output reg clk,
output reg RESET,
output reg [9:0] rx_code_group_out,
input [7:0] RXD,
input RX_DV,
input RX_ER
);



initial begin
clk=0;
RESET=1;
//Prueba de funcionamiento correcto de la maquina
#5 rx_code_group_out=10'b1100000101;//K28.5
#2 rx_code_group_out=10'b1010010110;//D5.6/D16.2
#2 rx_code_group_out=10'b1100000101;//K28.5
#2 rx_code_group_out=10'b1010010110;//D5.6/D16.2
#2 rx_code_group_out=10'b1100000101;//K28.5
#2 rx_code_group_out=10'b1010010110;//D5.6/D16.2
#2 rx_code_group_out=10'b1101101000;//k27.7 S par
#2 rx_code_group_out=10'b1001110100;//D0.0 impar
#2 rx_code_group_out=10'b1000101011;//D1.0 par
#2 rx_code_group_out=10'b1011010100;//D2.0 impar
#2 rx_code_group_out=10'b1100010100;//D3.0 par
#2 rx_code_group_out=10'b1101010100;//D4.0 impar
#2 rx_code_group_out=10'b1010011011;//D5.0 par
#2 rx_code_group_out=10'b0110011011;//D6.0 impar
#2 rx_code_group_out=10'b0001110100;//D7.0 par
#2 rx_code_group_out=10'b0001101011;//D8.0 impar
#2 rx_code_group_out= 10'b0100010111;//k29.7 T par
#2 rx_code_group_out= 10'b0001010111;;//k23.7 R impar
#2 rx_code_group_out=10'b1100000101;//K28.5 par
//Prueba de no inicio del paquete
#5 RESET=0;
#2 RESET=1;
#5 rx_code_group_out=10'b1100000101;//K28.5
#2 rx_code_group_out=10'b1010010110;//D5.6/D16.2
#2 rx_code_group_out=10'b1100000101;//K28.5
#2 rx_code_group_out=10'b1010010110;//D5.6/D16.2
#2 rx_code_group_out=10'b1100000101;//K28.5
#2 rx_code_group_out=10'b1010010110;//D5.6/D16.2
#2 rx_code_group_out=10'b1010010110;//D5.6/D16.2
//#2 rx_code_group_out=10'b1101101000;//k27.7 S par
#2 rx_code_group_out=10'b1001110100;//D0.0 impar
#2 rx_code_group_out=10'b1000101011;//D1.0 par
#2 rx_code_group_out=10'b1011010100;//D2.0 impar
#2 rx_code_group_out=10'b1100010100;//D3.0 par
#2 rx_code_group_out=10'b1101010100;//D4.0 impar
#2 rx_code_group_out=10'b1010011011;//D5.0 par
#2 rx_code_group_out=10'b0110011011;//D6.0 impar
#2 rx_code_group_out=10'b0001110100;//D7.0 par
#2 rx_code_group_out=10'b0001101011;//D8.0 impar
#2 rx_code_group_out= 10'b0100010111;//k29.7 T par
#2 rx_code_group_out= 10'b0001010111;;//k23.7 R impar
#2 rx_code_group_out=10'b1100000101;//K28.5 par

//Prueba de code_group invalido 
#5 RESET=0;
#2 RESET=1;
#5 rx_code_group_out=10'b1100000101;//K28.5
#2 rx_code_group_out=10'b1010010110;//D5.6/D16.2
#2 rx_code_group_out=10'b1100000101;//K28.5
#2 rx_code_group_out=10'b1010010110;//D5.6/D16.2
#2 rx_code_group_out=10'b1100000101;//K28.5
#2 rx_code_group_out=10'b1010010110;//D5.6/D16.2
#2 rx_code_group_out=10'b1101101000;//k27.7 S par
#2 rx_code_group_out=10'b1001110100;//D0.0 impar
#2 rx_code_group_out=10'b0000000000;//D invalido
#2 rx_code_group_out=10'b1011010100;//D2.0 impar
#2 rx_code_group_out=10'b1100010100;//D3.0 par
#2 rx_code_group_out=10'b1101010100;//D4.0 impar
#2 rx_code_group_out=10'b1010011011;//D5.0 par
#2 rx_code_group_out=10'b0110011011;//D6.0 impar
#2 rx_code_group_out=10'b0001110100;//D7.0 par
#2 rx_code_group_out=10'b0001101011;//D8.0 impar
#2 rx_code_group_out= 10'b0100010111;//k29.7 T par
#2 rx_code_group_out= 10'b0001010111;;//k23.7 R impar
#2 rx_code_group_out=10'b1100000101;//K28.5 par
//Prueba de no finalizacion de la cadena 
#5 RESET=0;
#2 RESET=1;
#5 rx_code_group_out=10'b1100000101;//K28.5
#2 rx_code_group_out=10'b1010010110;//D5.6/D16.2
#2 rx_code_group_out=10'b1100000101;//K28.5
#2 rx_code_group_out=10'b1010010110;//D5.6/D16.2
#2 rx_code_group_out=10'b1100000101;//K28.5
#2 rx_code_group_out=10'b1010010110;//D5.6/D16.2
#2 rx_code_group_out=10'b1101101000;//k27.7 S par
#2 rx_code_group_out=10'b1001110100;//D0.0 impar
#2 rx_code_group_out=10'b1000101011;//D1.0 par
#2 rx_code_group_out=10'b1011010100;//D2.0 impar
#2 rx_code_group_out=10'b1100010100;//D3.0 par
#2 rx_code_group_out=10'b1101010100;//D4.0 impar
#2 rx_code_group_out=10'b1010011011;//D5.0 par
#2 rx_code_group_out=10'b0110011011;//D6.0 impar
#2 rx_code_group_out=10'b0001110100;//D7.0 par
#2 rx_code_group_out=10'b0001101011;//D8.0 impar
#2 rx_code_group_out=10'b1100010100;//D3.0 par
#2 rx_code_group_out= 10'b0001010111;;//k23.7 R impar
#2 rx_code_group_out=10'b1100000101;//K28.5 par






#50
#10 $finish;
end 


always begin
#1 clk = !clk;
end

endmodule

Receive/Receive.v

//`include "dictionary_rd.v"

module Receive(
clk,
RESET,
rx_code_group_out,
RXD,//7:0
RX_DV,
RX_ER

);

//-----------Estados------------
parameter WAIT_FOR_K = 8'h1;
parameter RX_K = 8'h2;
parameter IDE_D = 8'h4;
parameter START_OF_PACKET = 8'h8;
parameter RECEIVE = 8'h10;
parameter RX_DATA = 8'h20;
parameter TRI_RRI_1 = 8'h40;
parameter TRI_RRI_2 = 8 'h80;


//-----------Inputs------------
input clk, RESET;
input [9:0] rx_code_group_out;
//-----------outputs-----------
output reg RX_DV, RX_ER;
output reg [7:0] RXD;
//------------Variables auxiliares--------
reg [12:0] state;
reg [12:0] nxt_state;
reg valid;//dato valido de los codegroups de control y datos 

//------------Code groups--------
reg [9:0] code_group [0:29];

//------------Codigo--------
always@(posedge clk)begin//flipflops maquina de estado
	if(RESET)begin 
		
		state<= nxt_state;//cambiar de estado
		
		if(rx_code_group_out==10'b1010010110) RXD<=8'hC5;//D5.6
        else if(rx_code_group_out==10'b1001000101) RXD<=8'h50;//D16.2
        else if(rx_code_group_out==10'b1100000101||rx_code_group_out==10'b0011111010) RXD<=8'hBC; //k28.5
        else if(rx_code_group_out==10'b1101101000||rx_code_group_out==10'b0010010111) RXD<=8'h55; //S
        else if(rx_code_group_out==10'b1001110100||rx_code_group_out==10'b0110001011) RXD<=8'h00; //D0.0
        else if(rx_code_group_out==10'b0111010100||rx_code_group_out==10'b1000101011) RXD<=8'h01; //D1.0
        else if(rx_code_group_out==10'b1011010100||rx_code_group_out==10'b0100101011) RXD<=8'h02; //D2.0
        else if(rx_code_group_out==10'b1100011011||rx_code_group_out==10'b1100010100) RXD<=8'h03; //D3.0
        else if(rx_code_group_out==10'b1101010100||rx_code_group_out==10'b0010101011) RXD<=8'h04; //D4.0
        else if(rx_code_group_out==10'b1010011011||rx_code_group_out==10'b1010010100) RXD<=8'h05; //D5.0
        else if(rx_code_group_out==10'b0110011011||rx_code_group_out==10'b0110010100) RXD<=8'h06; //D6.0
        else if(rx_code_group_out==10'b1110001011||rx_code_group_out==10'b0001110100) RXD<=8'h07; //D7.0
        else if(rx_code_group_out==10'b0001101011||rx_code_group_out==10'b1110010100) RXD<=8'h08; //D8.0
        else if(rx_code_group_out==10'b1001011011||rx_code_group_out==10'b1001010100) RXD<=8'h09; //D9.0
        else if(rx_code_group_out==10'b0100010111||rx_code_group_out==10'b1011101000) RXD<=8'hFD; //K29.7
        else if(rx_code_group_out==10'b1110101000||rx_code_group_out==10'b0001010111) RXD<=8'hF7; //K23.7


	end else begin //reset de todas las salidas y variables auxiliares del modulo
		
		nxt_state<=WAIT_FOR_K;
		RX_DV<=0; 
		RX_ER<=0;

		
	end
end


always @(*)begin

	nxt_state = state;//inicializacion
	
	case(state)//un case para pasar de estado en estado
		
		
		WAIT_FOR_K: begin//1
			
			if(rx_code_group_out==10'b1100000101)begin// k28.5 par

				RX_DV=0;
				RX_ER=0;
				nxt_state = RX_K;

			end else nxt_state = WAIT_FOR_K;

			
		end
	
		RX_K: begin //2

			if(rx_code_group_out==10'b1010010110 || rx_code_group_out==10'b1001000101 )begin//D5.6/D16.2 impar
				RX_DV=0;
				RX_ER=0;
				nxt_state = IDE_D;
			end else nxt_state = WAIT_FOR_K;
		end

		IDE_D: begin//si hay una coma par 4

			if(rx_code_group_out==10'b1101101000)begin//S par/impar
				RX_DV=0;
				RX_ER=0;
				nxt_state = START_OF_PACKET;
			end else nxt_state = RX_K;
			
		end

		START_OF_PACKET: begin//8

			RX_DV=1;
			RX_ER=0;	
			nxt_state = RECEIVE;

		end 
//10
		RECEIVE: begin //si hay una coma par

		if(valid)begin	
			if(rx_code_group_out==10'b0100010111 )begin//T par 
				RX_ER=0;
				nxt_state = TRI_RRI_1;
			end else nxt_state = RX_DATA;
		end else begin
		RX_ER=1;
		nxt_state = RECEIVE; 
		end
			
		end

//20	
	

		RX_DATA: begin  //datos pares e impares

			if(valid)begin
					//decode ?
				RX_ER=0;
				nxt_state=RECEIVE;

			end else 
			begin
				//decode ?
				RX_ER=1;
				nxt_state=RECEIVE;
			end
	
		end
//40
		TRI_RRI_1: begin //40


		if(rx_code_group_out==10'b0001010111/*k23.7/R*/ )begin//R impar
				RX_DV=0;
				nxt_state = TRI_RRI_2;
			end else nxt_state = RECEIVE;
			
		end
//80

		TRI_RRI_2: begin //80

			if(rx_code_group_out==10'b1100000101/*k28.5/I*/ )begin//I par

				RX_DV=0;
				RX_ER=0;
				nxt_state = RX_K;

			end else nxt_state = RECEIVE;

		end


		default: nxt_state = WAIT_FOR_K;//si no pasa nada se pasa al primer estado
	endcase
	
end

always@(posedge clk)begin


	code_group[0]= 10'b1010010110; //D5.6 impar= 1010010110
 	code_group[1]= 10'b1001000101; 	//D16.2 impar=1001000101
	code_group[2]= 10'b1100000101;	// K28.5 par=1100000101
	code_group[3]= 10'b0011111010; //K28.5 impar=0011111010
	code_group[4]= 10'b1101101000; //K27.7 impar=1101101000
	code_group[5]= 10'b0010010111; //K27.7 par=0010010111
	code_group[6]= 10'b1001110100; //D0.0 impar=1001110100\
	code_group[7]= 10'b0110001011; //D0.0 par=0110001011
	code_group[8]= 10'b0111010100; //D1.0 impar=0111010100
	code_group[9]= 10'b1000101011;//D1.0 par=1000101011
	code_group[10]= 10'b1011010100;//D2.0 impar=1011010100
	code_group[11]= 10'b0100101011;//D2.0 par=0100101011
	code_group[12]= 10'b1100011011;//D3.0 impar=1100011011
	code_group[13]= 10'b1100010100;//D3.0 par=1100010100
	code_group[14]= 10'b1101010100;//D4.0 impar=1101010100
	code_group[15]= 10'b0010101011;//D4.0 par=0010101011
	code_group[16]= 10'b1010011011;//D5.0 impar=1010011011
	code_group[17]= 10'b1010010100;//D5.0 par=1010010100
	code_group[18]= 10'b0110011011;//D6.0 impar=0110011011
	code_group[19]= 10'b0110010100;//D6.0 par=0110010100
	code_group[20]= 10'b1110001011;//D7.0 impar=1110001011
	code_group[21]= 10'b0001110100;//D7.0 par=0001110100
	code_group[22]= 10'b0001101011;//D8.0 par=0001101011
	code_group[23]= 10'b1110010100;//D8.0 impar=1110010100
	code_group[24]= 10'b1001011011;//D9.0 impar=1001011011
	code_group[25]= 10'b1001010100;//D9.0 par=1001010100
	code_group[26]= 10'b0100010111;//K29.7=0100010111 par
	code_group[27]= 10'b1011101000;//K29.7=1011101000 impar
	code_group[28]= 10'b1110101000;//k23.7 R par
	code_group[29]= 10'b0001010111;//k23.7 R impar

	//si se cumple que el dato esta en la lista el code group es valido 
	if(rx_code_group_out==code_group[0]||rx_code_group_out==code_group[1]||rx_code_group_out==code_group[2]||rx_code_group_out==code_group[3]||rx_code_group_out==code_group[4]
	||rx_code_group_out==code_group[5]||rx_code_group_out==code_group[6]||rx_code_group_out==code_group[7]||rx_code_group_out==code_group[8]||rx_code_group_out==code_group[9]
	||rx_code_group_out==code_group[10]||rx_code_group_out==code_group[11]||rx_code_group_out==code_group[12]||rx_code_group_out==code_group[13]||rx_code_group_out==code_group[14]
	||rx_code_group_out==code_group[15]||rx_code_group_out==code_group[16]||rx_code_group_out==code_group[17]||rx_code_group_out==code_group[18]||rx_code_group_out==code_group[19]
	||rx_code_group_out==code_group[20]||rx_code_group_out==code_group[21]||rx_code_group_out==code_group[22]||rx_code_group_out==code_group[23]||rx_code_group_out==code_group[24]
	||rx_code_group_out==code_group[25]||rx_code_group_out==code_group[26]||rx_code_group_out==code_group[27]||rx_code_group_out==code_group[28]||rx_code_group_out==code_group[29]
	)begin
	valid=1;
	
	end else valid=0;


end



endmodule

Receive/testbench.v
//se incluyen los otros modulos

`include "Receive.v"
`include "tester.v"
//`include "decoder.v"
module testbench;

wire clk;
wire RESET;
wire [9:0] rx_code_group_out;
wire [7:0] RXD;
wire RX_DV;
wire RX_ER;
//wire [7:0] a;

//se genera el archivo gtkwave
initial begin

  $dumpfile("resultados.vcd");
  $dumpvars;
  

end

//Modulo receive

Receive r1(
.clk(clk),
.RESET(RESET),
.rx_code_group_out(rx_code_group_out),
.RXD(RXD),
.RX_DV(RX_DV),
.RX_ER(RX_ER)
);

//modulo tester

probador senales(
.clk(clk),
.RESET(RESET),
.rx_code_group_out(rx_code_group_out),
.RXD(RXD),
.RX_DV(RX_DV),
.RX_ER(RX_ER)
);

endmodule

Receive/resultados.vcd
$date
	Sat Dec  3 10:09:37 2022
$end
$version
	Icarus Verilog
$end
$timescale
	1ns
$end
$scope module testbench $end
$var wire 10 ! rx_code_group_out [9:0] $end
$var wire 1 " clk $end
$var wire 1 # RX_ER $end
$var wire 1 $ RX_DV $end
$var wire 8 % RXD [7:0] $end
$var wire 1 & RESET $end
$scope module r1 $end
$var wire 10 ' rx_code_group_out [9:0] $end
$var wire 1 " clk $end
$var wire 1 & RESET $end
$var reg 8 ( RXD [7:0] $end
$var reg 1 $ RX_DV $end
$var reg 1 # RX_ER $end
$var reg 13 ) nxt_state [12:0] $end
$var reg 13 * state [12:0] $end
$var reg 1 + valid $end
$upscope $end
$scope module senales $end
$var wire 8 , RXD [7:0] $end
$var wire 1 $ RX_DV $end
$var wire 1 # RX_ER $end
$var reg 1 & RESET $end
$var reg 1 " clk $end
$var reg 10 - rx_code_group_out [9:0] $end
$upscope $end
$upscope $end
$enddefinitions $end
#0
$dumpvars
bx -
bx ,
x+
bx *
bx )
bx (
bx '
1&
bx %
x$
x#
0"
bx !
$end
#1
b1 )
0+
1"
#2
0"
#3
b1 *
1"
#4
0"
#5
b10111100 %
b10111100 (
b10111100 ,
b10 *
1+
b1 )
0#
0$
1"
b1100000101 !
b1100000101 '
b1100000101 -
#6
0"
#7
b11000101 %
b11000101 (
b11000101 ,
b100 *
b10 )
1"
b1010010110 !
b1010010110 '
b1010010110 -
#8
0"
#9
b10111100 %
b10111100 (
b10111100 ,
b10 *
b1 )
1"
b1100000101 !
b1100000101 '
b1100000101 -
#10
0"
#11
b11000101 %
b11000101 (
b11000101 ,
b100 *
b10 )
1"
b1010010110 !
b1010010110 '
b1010010110 -
#12
0"
#13
b10111100 %
b10111100 (
b10111100 ,
b10 *
b1 )
1"
b1100000101 !
b1100000101 '
b1100000101 -
#14
0"
#15
b11000101 %
b11000101 (
b11000101 ,
b100 *
b10 )
1"
b1010010110 !
b1010010110 '
b1010010110 -
#16
0"
#17
1$
b1010101 %
b1010101 (
b1010101 ,
b1000 *
b10000 )
1"
b1101101000 !
b1101101000 '
b1101101000 -
#18
0"
#19
b0 %
b0 (
b0 ,
b10000 *
b100000 )
1"
b1001110100 !
b1001110100 '
b1001110100 -
#20
0"
#21
b1 %
b1 (
b1 ,
b100000 *
b10000 )
1"
b1000101011 !
b1000101011 '
b1000101011 -
#22
0"
#23
b10 %
b10 (
b10 ,
b10000 *
b100000 )
1"
b1011010100 !
b1011010100 '
b1011010100 -
#24
0"
#25
b11 %
b11 (
b11 ,
b100000 *
b10000 )
1"
b1100010100 !
b1100010100 '
b1100010100 -
#26
0"
#27
b100 %
b100 (
b100 ,
b10000 *
b100000 )
1"
b1101010100 !
b1101010100 '
b1101010100 -
#28
0"
#29
b101 %
b101 (
b101 ,
b100000 *
b10000 )
1"
b1010011011 !
b1010011011 '
b1010011011 -
#30
0"
#31
b110 %
b110 (
b110 ,
b10000 *
b100000 )
1"
b110011011 !
b110011011 '
b110011011 -
#32
0"
#33
b111 %
b111 (
b111 ,
b100000 *
b10000 )
1"
b1110100 !
b1110100 '
b1110100 -
#34
0"
#35
b1000 %
b1000 (
b1000 ,
b10000 *
b100000 )
1"
b1101011 !
b1101011 '
b1101011 -
#36
0"
#37
b11111101 %
b11111101 (
b11111101 ,
b1000000 *
b10000 )
1"
b100010111 !
b100010111 '
b100010111 -
#38
0"
#39
b11110111 %
b11110111 (
b11110111 ,
b10000000 *
0$
b10000 )
1"
b1010111 !
b1010111 '
b1010111 -
#40
0"
#41
b10111100 %
b10111100 (
b10111100 ,
b10 *
b1 )
1"
b1100000101 !
b1100000101 '
b1100000101 -
#42
0"
#43
b10 )
b1 *
1"
#44
0"
#45
b1 )
b10 *
1"
#46
0"
0&
#47
1"
#48
0"
1&
#49
b10 )
b1 *
1"
#50
0"
#51
b1 )
b10 *
1"
#52
0"
#53
b10 )
b1 *
1"
#54
0"
#55
b11000101 %
b11000101 (
b11000101 ,
b1 )
1"
b1010010110 !
b1010010110 '
b1010010110 -
#56
0"
#57
b10111100 %
b10111100 (
b10111100 ,
b10 *
b1 )
1"
b1100000101 !
b1100000101 '
b1100000101 -
#58
0"
#59
b11000101 %
b11000101 (
b11000101 ,
b100 *
b10 )
1"
b1010010110 !
b1010010110 '
b1010010110 -
#60
0"
#61
b10111100 %
b10111100 (
b10111100 ,
b10 *
b1 )
1"
b1100000101 !
b1100000101 '
b1100000101 -
#62
0"
#63
b11000101 %
b11000101 (
b11000101 ,
b100 *
b10 )
1"
b1010010110 !
b1010010110 '
b1010010110 -
#64
0"
#65
b100 )
b10 *
1"
#66
0"
#67
b0 %
b0 (
b0 ,
b1 *
b1 )
1"
b1001110100 !
b1001110100 '
b1001110100 -
#68
0"
#69
b1 %
b1 (
b1 ,
1"
b1000101011 !
b1000101011 '
b1000101011 -
#70
0"
#71
b10 %
b10 (
b10 ,
1"
b1011010100 !
b1011010100 '
b1011010100 -
#72
0"
#73
b11 %
b11 (
b11 ,
1"
b1100010100 !
b1100010100 '
b1100010100 -
#74
0"
#75
b100 %
b100 (
b100 ,
1"
b1101010100 !
b1101010100 '
b1101010100 -
#76
0"
#77
b101 %
b101 (
b101 ,
1"
b1010011011 !
b1010011011 '
b1010011011 -
#78
0"
#79
b110 %
b110 (
b110 ,
1"
b110011011 !
b110011011 '
b110011011 -
#80
0"
#81
b111 %
b111 (
b111 ,
1"
b1110100 !
b1110100 '
b1110100 -
#82
0"
#83
b1000 %
b1000 (
b1000 ,
1"
b1101011 !
b1101011 '
b1101011 -
#84
0"
#85
b11111101 %
b11111101 (
b11111101 ,
1"
b100010111 !
b100010111 '
b100010111 -
#86
0"
#87
b11110111 %
b11110111 (
b11110111 ,
1"
b1010111 !
b1010111 '
b1010111 -
#88
0"
#89
b10111100 %
b10111100 (
b10111100 ,
b10 *
b1 )
1"
b1100000101 !
b1100000101 '
b1100000101 -
#90
0"
#91
b10 )
b1 *
1"
#92
0"
#93
b1 )
b10 *
1"
#94
0"
0&
#95
1"
#96
0"
1&
#97
b10 )
b1 *
1"
#98
0"
#99
b1 )
b10 *
1"
#100
0"
#101
b10 )
b1 *
1"
#102
0"
#103
b11000101 %
b11000101 (
b11000101 ,
b1 )
1"
b1010010110 !
b1010010110 '
b1010010110 -
#104
0"
#105
b10111100 %
b10111100 (
b10111100 ,
b10 *
b1 )
1"
b1100000101 !
b1100000101 '
b1100000101 -
#106
0"
#107
b11000101 %
b11000101 (
b11000101 ,
b100 *
b10 )
1"
b1010010110 !
b1010010110 '
b1010010110 -
#108
0"
#109
b10111100 %
b10111100 (
b10111100 ,
b10 *
b1 )
1"
b1100000101 !
b1100000101 '
b1100000101 -
#110
0"
#111
b11000101 %
b11000101 (
b11000101 ,
b100 *
b10 )
1"
b1010010110 !
b1010010110 '
b1010010110 -
#112
0"
#113
1$
b1010101 %
b1010101 (
b1010101 ,
b1000 *
b10000 )
1"
b1101101000 !
b1101101000 '
b1101101000 -
#114
0"
#115
b0 %
b0 (
b0 ,
b10000 *
b100000 )
1"
b1001110100 !
b1001110100 '
b1001110100 -
#116
0"
#117
b100000 *
1#
0+
b10000 )
1"
b0 !
b0 '
b0 -
#118
0"
#119
b10 %
b10 (
b10 ,
b10000 *
0#
1+
b100000 )
1"
b1011010100 !
b1011010100 '
b1011010100 -
#120
0"
#121
b11 %
b11 (
b11 ,
b100000 *
b10000 )
1"
b1100010100 !
b1100010100 '
b1100010100 -
#122
0"
#123
b100 %
b100 (
b100 ,
b10000 *
b100000 )
1"
b1101010100 !
b1101010100 '
b1101010100 -
#124
0"
#125
b101 %
b101 (
b101 ,
b100000 *
b10000 )
1"
b1010011011 !
b1010011011 '
b1010011011 -
#126
0"
#127
b110 %
b110 (
b110 ,
b10000 *
b100000 )
1"
b110011011 !
b110011011 '
b110011011 -
#128
0"
#129
b111 %
b111 (
b111 ,
b100000 *
b10000 )
1"
b1110100 !
b1110100 '
b1110100 -
#130
0"
#131
b1000 %
b1000 (
b1000 ,
b10000 *
b100000 )
1"
b1101011 !
b1101011 '
b1101011 -
#132
0"
#133
b11111101 %
b11111101 (
b11111101 ,
b1000000 *
b10000 )
1"
b100010111 !
b100010111 '
b100010111 -
#134
0"
#135
b11110111 %
b11110111 (
b11110111 ,
b10000000 *
0$
b10000 )
1"
b1010111 !
b1010111 '
b1010111 -
#136
0"
#137
b10111100 %
b10111100 (
b10111100 ,
b10 *
b1 )
1"
b1100000101 !
b1100000101 '
b1100000101 -
#138
0"
#139
b10 )
b1 *
1"
#140
0"
#141
b1 )
b10 *
1"
#142
0"
0&
#143
1"
#144
0"
1&
#145
b10 )
b1 *
1"
#146
0"
#147
b1 )
b10 *
1"
#148
0"
#149
b10 )
b1 *
1"
#150
0"
#151
b11000101 %
b11000101 (
b11000101 ,
b1 )
1"
b1010010110 !
b1010010110 '
b1010010110 -
#152
0"
#153
b10111100 %
b10111100 (
b10111100 ,
b10 *
b1 )
1"
b1100000101 !
b1100000101 '
b1100000101 -
#154
0"
#155
b11000101 %
b11000101 (
b11000101 ,
b100 *
b10 )
1"
b1010010110 !
b1010010110 '
b1010010110 -
#156
0"
#157
b10111100 %
b10111100 (
b10111100 ,
b10 *
b1 )
1"
b1100000101 !
b1100000101 '
b1100000101 -
#158
0"
#159
b11000101 %
b11000101 (
b11000101 ,
b100 *
b10 )
1"
b1010010110 !
b1010010110 '
b1010010110 -
#160
0"
#161
1$
b1010101 %
b1010101 (
b1010101 ,
b1000 *
b10000 )
1"
b1101101000 !
b1101101000 '
b1101101000 -
#162
0"
#163
b0 %
b0 (
b0 ,
b10000 *
b100000 )
1"
b1001110100 !
b1001110100 '
b1001110100 -
#164
0"
#165
b1 %
b1 (
b1 ,
b100000 *
b10000 )
1"
b1000101011 !
b1000101011 '
b1000101011 -
#166
0"
#167
b10 %
b10 (
b10 ,
b10000 *
b100000 )
1"
b1011010100 !
b1011010100 '
b1011010100 -
#168
0"
#169
b11 %
b11 (
b11 ,
b100000 *
b10000 )
1"
b1100010100 !
b1100010100 '
b1100010100 -
#170
0"
#171
b100 %
b100 (
b100 ,
b10000 *
b100000 )
1"
b1101010100 !
b1101010100 '
b1101010100 -
#172
0"
#173
b101 %
b101 (
b101 ,
b100000 *
b10000 )
1"
b1010011011 !
b1010011011 '
b1010011011 -
#174
0"
#175
b110 %
b110 (
b110 ,
b10000 *
b100000 )
1"
b110011011 !
b110011011 '
b110011011 -
#176
0"
#177
b111 %
b111 (
b111 ,
b100000 *
b10000 )
1"
b1110100 !
b1110100 '
b1110100 -
#178
0"
#179
b1000 %
b1000 (
b1000 ,
b10000 *
b100000 )
1"
b1101011 !
b1101011 '
b1101011 -
#180
0"
#181
b11 %
b11 (
b11 ,
b100000 *
b10000 )
1"
b1100010100 !
b1100010100 '
b1100010100 -
#182
0"
#183
b11110111 %
b11110111 (
b11110111 ,
b10000 *
b100000 )
1"
b1010111 !
b1010111 '
b1010111 -
#184
0"
#185
b10111100 %
b10111100 (
b10111100 ,
b100000 *
b10000 )
1"
b1100000101 !
b1100000101 '
b1100000101 -
#186
0"
#187
b100000 )
b10000 *
1"
#188
0"
#189
b10000 )
b100000 *
1"
#190
0"
#191
b100000 )
b10000 *
1"
#192
0"
#193
b10000 )
b100000 *
1"
#194
0"
#195
b100000 )
b10000 *
1"
#196
0"
#197
b10000 )
b100000 *
1"
#198
0"
#199
b100000 )
b10000 *
1"
#200
0"
#201
b10000 )
b100000 *
1"
#202
0"
#203
b100000 )
b10000 *
1"
#204
0"
#205
b10000 )
b100000 *
1"
#206
0"
#207
b100000 )
b10000 *
1"
#208
0"
#209
b10000 )
b100000 *
1"
#210
0"
#211
b100000 )
b10000 *
1"
#212
0"
#213
b10000 )
b100000 *
1"
#214
0"
#215
b100000 )
b10000 *
1"
#216
0"
#217
b10000 )
b100000 *
1"
#218
0"
#219
b100000 )
b10000 *
1"
#220
0"
#221
b10000 )
b100000 *
1"
#222
0"
#223
b100000 )
b10000 *
1"
#224
0"
#225
b10000 )
b100000 *
1"
#226
0"
#227
b100000 )
b10000 *
1"
#228
0"
#229
b10000 )
b100000 *
1"
#230
0"
#231
b100000 )
b10000 *
1"
#232
0"
#233
b10000 )
b100000 *
1"
#234
0"
#235
b100000 )
b10000 *
1"
#236
0"
#237
b10000 )
b100000 *
1"
#238
0"
#239
b100000 )
b10000 *
1"
#240
0"
#241
b10000 )
b100000 *
1"
#242
0"
#243
b100000 )
b10000 *
1"
#244
0"
#245
b10000 )
b100000 *
1"
